examples/showcase/svm_rechenberg_global_timeout.py
examples/showcase/n_class_saes_global_and_local_timeout.py
examples/showcase/featureselection_saes_global_timeout.py
examples/showcase/one_min_gridsearch.py
examples/showcase/README.rst
examples/showcase/sum_of_squares_saes_global_timeout.py
examples/showcase/svm_gridsearch_global_timeout.py
examples/showcase/__init__.py
metaopt-0.1.0.dist-info/WHEEL
metaopt-0.1.0.dist-info/DESCRIPTION.rst
metaopt-0.1.0.dist-info/METADATA
metaopt-0.1.0.dist-info/metadata.json
metaopt-0.1.0.dist-info/top_level.txt
metaopt-0.1.0.dist-info/RECORD
metaopt/__main__.py
metaopt/__init__.py
metaopt/objective/__init__.py
metaopt/objective/bool/one_min_eight.py
metaopt/objective/bool/__init__.py
metaopt/objective/bool/one_max_eight.py
metaopt/objective/integer/__init__.py
metaopt/objective/integer/failing/g.py
metaopt/objective/integer/failing/f.py
metaopt/objective/integer/failing/__init__.py
metaopt/objective/integer/fast/__init__.py
metaopt/objective/integer/fast/explicit/g.py
metaopt/objective/integer/fast/explicit/f.py
metaopt/objective/integer/fast/explicit/__init__.py
metaopt/objective/integer/fast/implicit/k.py
metaopt/objective/integer/fast/implicit/g.py
metaopt/objective/integer/fast/implicit/i.py
metaopt/objective/integer/fast/implicit/j.py
metaopt/objective/integer/fast/implicit/h.py
metaopt/objective/integer/fast/implicit/f.py
metaopt/objective/integer/fast/implicit/__init__.py
metaopt/objective/integer/slow/__init__.py
metaopt/objective/integer/slow/explicit/g.py
metaopt/objective/integer/slow/explicit/f.py
metaopt/objective/integer/slow/explicit/__init__.py
metaopt/objective/integer/slow/implicit/g.py
metaopt/objective/integer/slow/implicit/h.py
metaopt/objective/integer/slow/implicit/f.py
metaopt/objective/integer/slow/implicit/__init__.py
metaopt/plugin/plugin.py
metaopt/plugin/timeout.py
metaopt/plugin/base.py
metaopt/plugin/__init__.py
metaopt/plugin/util/invocation.py
metaopt/plugin/util/__init__.py
metaopt/plugin/visualization/best_fitness.py
metaopt/plugin/visualization/__init__.py
metaopt/plugin/visualization/landscape.py
metaopt/plugin/print/debug.py
